Workbook

Sheet Summary
B2: VYNE STRATEGIES
B3: Year 1 Startup Budget - Summary
B5: One-time startup costs | C5: =Assumptions!C39 -> 13950
B6: Monthly recurring — core opex (before Dakota) | C6: =Assumptions!C18 -> 1126
B7: Annualized core opex (x12, before Dakota) | C7: =C6*12 -> 13512
B8: Dakota (once triggered, annual) | C8: =Assumptions!C21 -> 6000
B9: Monthly discretionary & travel | C9: ='Discretionary & Travel'!C9 -> 1500
B10: Annualized discretionary & travel (x12) | C10: =C9*12 -> 18000
B12: TOTAL YEAR 1 CASH OUT (per Cash Flow tab) | C12: ='Year 1 Cash Flow'!O30 -> 48462
B15: Notes
B16: - Google Workspace used in place of Microsoft 365, per your direction.
B17: - CRM line is a placeholder - plug in your actual HubSpot or Salesforce tier once decided. Both support Claude API/MCP integration.
B18: - Dakota is modeled as deferred spend - toggle its start month on the Assumptions tab once you hit your inbound trigger.
B19: - Computer ($2,000), iPad ($2,000), apparel ($2,000), phone ($75/mo), and internet ($75/mo) are built in per your numbers.
B20: - Tech/systems setup is estimated at $3,500 for a contractor to link your CRM, Claude API, connectors, and agents - flagged yellow on Assumptions since it's a placeholder until you get quotes.
B21: - Entertainment ($1,000/mo) and travel (placeholder $500/mo) are tracked on a separate tab since they flex more and have different tax substantiation needs than core opex.
B22: - Attorney review and trademark figures are estimates - confirm with your attorney before finalizing.
B23: - This is a pre-revenue cost model. It does not include placement fee revenue or any personal salary draw.

Sheet Assumptions
B2: VYNE STRATEGIES — Year 1 Startup Budget
B3: Blue = editable inputs. Change any value here and the other tabs update automatically.
B5: MONTHLY RECURRING COSTS (core operating)
B6: Google Workspace (Business Standard, 1 user) | C6: 14 | D6: Google's per-user list price
B7: CRM — HubSpot or Salesforce (placeholder) | C7: 150 | D7: Update once you pick the platform; both connect to Claude via API/MCP
B8: Claude API budget (agents + connectors) | C8: 500 | D8: Your stated budget
B9: LinkedIn Sales Navigator | C9: 100 | D9: Core tier, single seat
B10: Domain + website hosting | C10: 15 | D10: Static HTML site, minimal hosting
B11: QuickBooks Online (Simple Start) | C11: 35 | D11: Upgrade to Essentials (~$65/mo) or Plus (~$99/mo) if needed
B12: Business insurance (E&O + general liability) | C12: 125 | D12: ~$1,500/yr amortized monthly
B13: Cell phone | C13: 75 | D13: Your stated cost
B14: Internet | C14: 75 | D14: Your stated cost
B15: Virtual mailbox / business address | C15: 20 | D15: Keeps address separate from employer/home
B16: Registered agent service | C16: 17 | D16: ~$200/yr amortized monthly
B18: Total monthly recurring (core) | C18: =SUM(C6:C16) -> 1126
B20: DEFERRED / TRIGGERED SPEND
B21: Dakota (data platform) — annual cost | C21: 6000 | D21: Deferred until inbound trigger is hit
B22: Dakota start month (1-12; use 13 = not this year) | C22: 7 | D22: Editable - flip this on when you're ready
B24: ONE-TIME STARTUP COSTS (see Startup Costs tab for full detail)
B25: LLC filing (state fee, varies) | C25: 300 | D25: Check your state's exact fee
B26: Registered agent - first year | C26: 200
B27: EIN (IRS) | C27: 0 | D27: Free
B28: Operating agreement (template or light attorney review) | C28: 300
B29: Attorney review - privacy policy, ToS, client agreements | C29: 2500 | D29: Flagged in your docs as needed before launch
B30: Trademark filing - "VYNE" (USPTO + light attorney help) | C30: 1100 | D30: $350 USPTO base + ~$750 attorney assist
B31: Business insurance setup / first premium | C31: 0 | D31: Captured in monthly recurring above
B32: Virtual mailbox setup fee | C32: 50
B33: Computer | C33: 2000 | D33: Your stated cost
B34: iPad | C34: 2000 | D34: Your stated cost
B35: Business cards / stationery | C35: 0 | D35: Deferred - brand stays unnamed/institutional for now
B36: Apparel | C36: 2000 | D36: Your stated cost
B37: Tech/systems setup — contractor to link CRM, Claude API, connectors, agents | C37: 3500 | D37: Estimate for a freelance ops/integration contractor; adjust once you get quotes
B39: Total one-time startup costs | C39: =SUM(C25:C37) -> 13950

Sheet Discretionary & Travel
B2: VYNE STRATEGIES — Discretionary & Travel Budget
B3: Kept separate from core opex — entertainment/travel spend has different tax substantiation rules and is easier to flex up/down.
B5: MONTHLY DISCRETIONARY SPEND
B6: Entertainment (client development, meals, etc.) | C6: 1000 | D6: Your stated budget
B7: Travel | C7: 500 | D7: Placeholder — adjust to your actual travel plan (this can swing a lot month to month)
B9: Total monthly discretionary | C9: =SUM(C6:C7) -> 1500
B10: Annualized (x12) | C10: =C9*12 -> 18000

Sheet Startup Costs
B2: VYNE STRATEGIES — One-Time Startup Costs
B3: All figures link to the Assumptions tab.
B5: Item | C5: Category | D5: Cost | E5: Notes
B6: LLC filing (state fee) | C6: Legal & Formation | D6: =Assumptions!C25 -> 300 | E6: =Assumptions!D25 -> Check your state's exact fee
B7: Registered agent - first year | C7: Legal & Formation | D7: =Assumptions!C26 -> 200 | E7: =Assumptions!D26 -> 0
B8: EIN (IRS) | C8: Legal & Formation | D8: =Assumptions!C27 -> 0 | E8: =Assumptions!D27 -> Free
B9: Operating agreement | C9: Legal & Formation | D9: =Assumptions!C28 -> 300 | E9: =Assumptions!D28 -> 0
B10: Attorney review (privacy policy, ToS, client agreements) | C10: Legal & Formation | D10: =Assumptions!C29 -> 2500 | E10: =Assumptions!D29 -> Flagged in your docs as needed before launch
B11: Trademark filing - "VYNE" | C11: Legal & Formation | D11: =Assumptions!C30 -> 1100 | E11: =Assumptions!D30 -> $350 USPTO base + ~$750 attorney assist
B12: Insurance setup | C12: Insurance | D12: =Assumptions!C31 -> 0 | E12: =Assumptions!D31 -> Captured in monthly recurring above
B13: Virtual mailbox setup fee | C13: Admin | D13: =Assumptions!C32 -> 50 | E13: =Assumptions!D32 -> 0
B14: Computer | C14: Equipment | D14: =Assumptions!C33 -> 2000 | E14: =Assumptions!D33 -> Your stated cost
B15: iPad | C15: Equipment | D15: =Assumptions!C34 -> 2000 | E15: =Assumptions!D34 -> Your stated cost
B16: Business cards / stationery | C16: Branding | D16: =Assumptions!C35 -> 0 | E16: =Assumptions!D35 -> Deferred - brand stays unnamed/institutional for now
B17: Apparel | C17: Branding | D17: =Assumptions!C36 -> 2000 | E17: =Assumptions!D36 -> Your stated cost
B18: Tech/systems setup — contractor | C18: Technology | D18: =Assumptions!C37 -> 3500 | E18: =Assumptions!D37 -> Estimate for a freelance ops/integration contractor; adjust once you get quotes
B19: TOTAL ONE-TIME STARTUP COSTS | D19: =SUM(D6:D18) -> 13950
B22: By Category
B23: Category | C23: Subtotal
B24: Legal & Formation | C24: =SUMIF($C$6:$C$18,B24,$D$6:$D$18) -> 4400
B25: Insurance | C25: =SUMIF($C$6:$C$18,B25,$D$6:$D$18) -> 0
B26: Admin | C26: =SUMIF($C$6:$C$18,B26,$D$6:$D$18) -> 50
B27: Equipment | C27: =SUMIF($C$6:$C$18,B27,$D$6:$D$18) -> 4000
B28: Branding | C28: =SUMIF($C$6:$C$18,B28,$D$6:$D$18) -> 2000
B29: Technology | C29: =SUMIF($C$6:$C$18,B29,$D$6:$D$18) -> 3500

Sheet Year 1 Cash Flow
B2: VYNE STRATEGIES — Year 1 Monthly Cash Flow (Costs Only)
B3: Pre-revenue expense view. Monthly recurring links to Assumptions; one-time costs land in Month 1.
B5: Expense | C5: Mo 1 | D5: Mo 2 | E5: Mo 3 | F5: Mo 4 | G5: Mo 5 | H5: Mo 6 | I5: Mo 7 | J5: Mo 8 | K5: Mo 9 | L5: Mo 10 | M5: Mo 11 | N5: Mo 12 | O5: Total
B6: ONE-TIME STARTUP COSTS
B7: Startup costs (from Startup Costs tab) | C7: ='Startup Costs'!D19 -> 13950 | D7: 0 | E7: 0 | F7: 0 | G7: 0 | H7: 0 | I7: 0 | J7: 0 | K7: 0 | L7: 0 | M7: 0 | N7: 0 | O7: =SUM(C7:N7) -> 13950
B9: MONTHLY RECURRING (core opex)
B10: Google Workspace | C10: =Assumptions!$C$6 -> 14 | D10: =Assumptions!$C$6 -> 14 | E10: =Assumptions!$C$6 -> 14 | F10: =Assumptions!$C$6 -> 14 | G10: =Assumptions!$C$6 -> 14 | H10: =Assumptions!$C$6 -> 14 | I10: =Assumptions!$C$6 -> 14 | J10: =Assumptions!$C$6 -> 14 | ... N10: =Assumptions!$C$6 -> 14 | O10: =SUM(C10:N10) -> 168
B11: CRM (HubSpot / Salesforce) | C11: =Assumptions!$C$7 -> 150 | D11: =Assumptions!$C$7 -> 150 | E11: =Assumptions!$C$7 -> 150 | F11: =Assumptions!$C$7 -> 150 | G11: =Assumptions!$C$7 -> 150 | H11: =Assumptions!$C$7 -> 150 | I11: =Assumptions!$C$7 -> 150 | J11: =Assumptions!$C$7 -> 150 | ... N11: =Assumptions!$C$7 -> 150 | O11: =SUM(C11:N11) -> 1800
B12: Claude API budget | C12: =Assumptions!$C$8 -> 500 | D12: =Assumptions!$C$8 -> 500 | E12: =Assumptions!$C$8 -> 500 | F12: =Assumptions!$C$8 -> 500 | G12: =Assumptions!$C$8 -> 500 | H12: =Assumptions!$C$8 -> 500 | I12: =Assumptions!$C$8 -> 500 | J12: =Assumptions!$C$8 -> 500 | ... N12: =Assumptions!$C$8 -> 500 | O12: =SUM(C12:N12) -> 6000
B13: LinkedIn Sales Navigator | C13: =Assumptions!$C$9 -> 100 | D13: =Assumptions!$C$9 -> 100 | E13: =Assumptions!$C$9 -> 100 | F13: =Assumptions!$C$9 -> 100 | G13: =Assumptions!$C$9 -> 100 | H13: =Assumptions!$C$9 -> 100 | I13: =Assumptions!$C$9 -> 100 | J13: =Assumptions!$C$9 -> 100 | ... N13: =Assumptions!$C$9 -> 100 | O13: =SUM(C13:N13) -> 1200
B14: Domain + hosting | C14: =Assumptions!$C$10 -> 15 | D14: =Assumptions!$C$10 -> 15 | E14: =Assumptions!$C$10 -> 15 | F14: =Assumptions!$C$10 -> 15 | G14: =Assumptions!$C$10 -> 15 | H14: =Assumptions!$C$10 -> 15 | I14: =Assumptions!$C$10 -> 15 | J14: =Assumptions!$C$10 -> 15 | ... N14: =Assumptions!$C$10 -> 15 | O14: =SUM(C14:N14) -> 180
B15: QuickBooks Online | C15: =Assumptions!$C$11 -> 35 | D15: =Assumptions!$C$11 -> 35 | E15: =Assumptions!$C$11 -> 35 | F15: =Assumptions!$C$11 -> 35 | G15: =Assumptions!$C$11 -> 35 | H15: =Assumptions!$C$11 -> 35 | I15: =Assumptions!$C$11 -> 35 | J15: =Assumptions!$C$11 -> 35 | ... N15: =Assumptions!$C$11 -> 35 | O15: =SUM(C15:N15) -> 420
B16: Business insurance | C16: =Assumptions!$C$12 -> 125 | D16: =Assumptions!$C$12 -> 125 | E16: =Assumptions!$C$12 -> 125 | F16: =Assumptions!$C$12 -> 125 | G16: =Assumptions!$C$12 -> 125 | H16: =Assumptions!$C$12 -> 125 | I16: =Assumptions!$C$12 -> 125 | J16: =Assumptions!$C$12 -> 125 | ... N16: =Assumptions!$C$12 -> 125 | O16: =SUM(C16:N16) -> 1500
B17: Cell phone | C17: =Assumptions!$C$13 -> 75 | D17: =Assumptions!$C$13 -> 75 | E17: =Assumptions!$C$13 -> 75 | F17: =Assumptions!$C$13 -> 75 | G17: =Assumptions!$C$13 -> 75 | H17: =Assumptions!$C$13 -> 75 | I17: =Assumptions!$C$13 -> 75 | J17: =Assumptions!$C$13 -> 75 | ... N17: =Assumptions!$C$13 -> 75 | O17: =SUM(C17:N17) -> 900
B18: Internet | C18: =Assumptions!$C$14 -> 75 | D18: =Assumptions!$C$14 -> 75 | E18: =Assumptions!$C$14 -> 75 | F18: =Assumptions!$C$14 -> 75 | G18: =Assumptions!$C$14 -> 75 | H18: =Assumptions!$C$14 -> 75 | I18: =Assumptions!$C$14 -> 75 | J18: =Assumptions!$C$14 -> 75 | ... N18: =Assumptions!$C$14 -> 75 | O18: =SUM(C18:N18) -> 900
B19: Virtual mailbox | C19: =Assumptions!$C$15 -> 20 | D19: =Assumptions!$C$15 -> 20 | E19: =Assumptions!$C$15 -> 20 | F19: =Assumptions!$C$15 -> 20 | G19: =Assumptions!$C$15 -> 20 | H19: =Assumptions!$C$15 -> 20 | I19: =Assumptions!$C$15 -> 20 | J19: =Assumptions!$C$15 -> 20 | ... N19: =Assumptions!$C$15 -> 20 | O19: =SUM(C19:N19) -> 240
B20: Registered agent (monthly amort.) | C20: =Assumptions!$C$16 -> 17 | D20: =Assumptions!$C$16 -> 17 | E20: =Assumptions!$C$16 -> 17 | F20: =Assumptions!$C$16 -> 17 | G20: =Assumptions!$C$16 -> 17 | H20: =Assumptions!$C$16 -> 17 | I20: =Assumptions!$C$16 -> 17 | J20: =Assumptions!$C$16 -> 17 | ... N20: =Assumptions!$C$16 -> 17 | O20: =SUM(C20:N20) -> 204
B21: Dakota (starts trigger month, /12) | C21: =IF(1>=Assumptions!$C$22,Assumptions!$C$21/12,0) -> 0 | D21: =IF(2>=Assumptions!$C$22,Assumptions!$C$21/12,0) -> 0 | E21: =IF(3>=Assumptions!$C$22,Assumptions!$C$21/12,0) -> 0 | F21: =IF(4>=Assumptions!$C$22,Assumptions!$C$21/12,0) -> 0 | G21: =IF(5>=Assumptions!$C$22,Assumptions!$C$21/12,0) -> 0 | H21: =IF(6>=Assumptions!$C$22,Assumptions!$C$21/12,0) -> 0 | I21: =IF(7>=Assumptions!$C$22,Assumptions!$C$21/12,0) -> 500 | J21: =IF(8>=Assumptions!$C$22,Assumptions!$C$21/12,0) -> 500 | K21: =IF(9>=Assumptions!$C$22,Assumptions!$C$21/12,0) -> 500 | L21: =IF(10>=Assumptions!$C$22,Assumptions!$C$21/12,0) -> 500 | M21: =IF(11>=Assumptions!$C$22,Assumptions!$C$21/12,0) -> 500 | N21: =IF(12>=Assumptions!$C$22,Assumptions!$C$21/12,0) -> 500 | O21: =SUM(C21:N21) -> 3000
B23: Subtotal - core recurring | C23: =SUM(C10,C11,C12,C13,C14,C15,C16,C17,C18,C19,C20,C21) -> 1126 | D23: =SUM(D10,D11,D12,D13,D14,D15,D16,D17,D18,D19,D20,D21) -> 1126 | E23: =SUM(E10,E11,E12,E13,E14,E15,E16,E17,E18,E19,E20,E21) -> 1126 | F23: =SUM(F10,F11,F12,F13,F14,F15,F16,F17,F18,F19,F20,F21) -> 1126 | G23: =SUM(G10,G11,G12,G13,G14,G15,G16,G17,G18,G19,G20,G21) -> 1126 | H23: =SUM(H10,H11,H12,H13,H14,H15,H16,H17,H18,H19,H20,H21) -> 1126 | I23: =SUM(I10,I11,I12,I13,I14,I15,I16,I17,I18,I19,I20,I21) -> 1626 | J23: =SUM(J10,J11,J12,J13,J14,J15,J16,J17,J18,J19,J20,J21) -> 1626 | ... N23: =SUM(N10,N11,N12,N13,N14,N15,N16,N17,N18,N19,N20,N21) -> 1626 | O23: =SUM(C23:N23) -> 16512
B25: DISCRETIONARY & TRAVEL
B26: Entertainment | C26: ='Discretionary & Travel'!$C$6 -> 1000 | D26: ='Discretionary & Travel'!$C$6 -> 1000 | E26: ='Discretionary & Travel'!$C$6 -> 1000 | F26: ='Discretionary & Travel'!$C$6 -> 1000 | G26: ='Discretionary & Travel'!$C$6 -> 1000 | H26: ='Discretionary & Travel'!$C$6 -> 1000 | I26: ='Discretionary & Travel'!$C$6 -> 1000 | J26: ='Discretionary & Travel'!$C$6 -> 1000 | ... N26: ='Discretionary & Travel'!$C$6 -> 1000 | O26: =SUM(C26:N26) -> 12000
B27: Travel | C27: ='Discretionary & Travel'!$C$7 -> 500 | D27: ='Discretionary & Travel'!$C$7 -> 500 | E27: ='Discretionary & Travel'!$C$7 -> 500 | F27: ='Discretionary & Travel'!$C$7 -> 500 | G27: ='Discretionary & Travel'!$C$7 -> 500 | H27: ='Discretionary & Travel'!$C$7 -> 500 | I27: ='Discretionary & Travel'!$C$7 -> 500 | J27: ='Discretionary & Travel'!$C$7 -> 500 | ... N27: ='Discretionary & Travel'!$C$7 -> 500 | O27: =SUM(C27:N27) -> 6000
B28: Subtotal - discretionary & travel | C28: =SUM(C26,C27) -> 1500 | D28: =SUM(D26,D27) -> 1500 | E28: =SUM(E26,E27) -> 1500 | F28: =SUM(F26,F27) -> 1500 | G28: =SUM(G26,G27) -> 1500 | H28: =SUM(H26,H27) -> 1500 | I28: =SUM(I26,I27) -> 1500 | J28: =SUM(J26,J27) -> 1500 | ... N28: =SUM(N26,N27) -> 1500 | O28: =SUM(C28:N28) -> 18000
B30: TOTAL MONTHLY SPEND | C30: =C7+C23+C28 -> 16576 | D30: =D7+D23+D28 -> 2626 | E30: =E7+E23+E28 -> 2626 | F30: =F7+F23+F28 -> 2626 | G30: =G7+G23+G28 -> 2626 | H30: =H7+H23+H28 -> 2626 | I30: =I7+I23+I28 -> 3126 | J30: =J7+J23+J28 -> 3126 | ... N30: =N7+N23+N28 -> 3126 | O30: =SUM(C30:N30) -> 48462
B32: Cumulative spend | C32: =C30 -> 16576 | D32: =C32+D30 -> 19202 | E32: =D32+E30 -> 21828 | F32: =E32+F30 -> 24454 | G32: =F32+G30 -> 27080 | H32: =G32+H30 -> 29706 | I32: =H32+I30 -> 32832 | J32: =I32+J30 -> 35958 | K32: =J32+K30 -> 39084 | ... N32: =M32+N30 -> 48462
